LICENSE
MANIFEST.in
README.md
setup.py
django_protected_media.egg-info/PKG-INFO
django_protected_media.egg-info/SOURCES.txt
django_protected_media.egg-info/dependency_links.txt
django_protected_media.egg-info/top_level.txt
protected_media/__init__.py
protected_media/admin.py
protected_media/apps.py
protected_media/models.py
protected_media/settings.py
protected_media/urls.py
protected_media/utils.py
protected_media/views.py
protected_media/migrations/__init__.py
tests/__init__.py
tests/settings.py
tests/test_protected_media.py